satchmo_payment_payworld
